{"id": 16113, "slug": "sleeping-dogs", "name": "Sleeping Dogs", "metacritic": 81, "released": "2012-08-14", "tba": false, "updated": "2019-09-17T03:12:58", "website": "http://sleepingdogs.net", "rating": 4.04, "rating_top": 4, "added_by_status": {"yet": 69, "owned": 2233, "beaten": 498, "toplay": 36, "dropped": 136, "playing": 10}, "playtime": 14, "achievements_count": 186, "ratings_count": 560, "suggestions_count": 606, "game_series_count": 0, "reviews_count": 561, "platforms": ["PC", "Xbox 360", "PlayStation 3"], "developers": ["United Front Games"], "genres": ["Action", "Shooter"], "publishers": ["Square Enix"], "esrb_rating": "Mature"}