{"id": 17186, "slug": "splatter-zombie-apocalypse", "name": "Splatter - Zombie Apocalypse", "metacritic": null, "released": "2014-06-04", "tba": false, "updated": "2019-09-17T04:45:44", "website": "", "rating": 2.45, "rating_top": 3, "added_by_status": {"yet": 11, "owned": 491, "beaten": 1, "toplay": 1, "dropped": 11}, "playtime": 4, "achievements_count": 36, "ratings_count": 29, "suggestions_count": 428, "game_series_count": 0, "reviews_count": 29, "platforms": ["Linux", "macOS", "PC"], "developers": ["Dreamworlds"], "genres": ["Action", "Adventure", "RPG", "Strategy", "Simulation", "Sports", "Racing", "Casual", "Indie"], "publishers": ["Dreamworlds"], "esrb_rating": null}